yowasp_nextpnr_ice40/__init__.py
yowasp_nextpnr_ice40/icebram.wasm
yowasp_nextpnr_ice40/icemulti.wasm
yowasp_nextpnr_ice40/icepack.wasm
yowasp_nextpnr_ice40/icepll.wasm
yowasp_nextpnr_ice40/nextpnr-ice40.wasm
yowasp_nextpnr_ice40/share/ice40/chipdb-1k.bin
yowasp_nextpnr_ice40/share/ice40/chipdb-384.bin
yowasp_nextpnr_ice40/share/ice40/chipdb-5k.bin
yowasp_nextpnr_ice40/share/ice40/chipdb-8k.bin
yowasp_nextpnr_ice40/share/ice40/chipdb-u4k.bin
yowasp_nextpnr_ice40-0.9.0.0.post686.dist-info/METADATA
yowasp_nextpnr_ice40-0.9.0.0.post686.dist-info/WHEEL
yowasp_nextpnr_ice40-0.9.0.0.post686.dist-info/entry_points.txt
yowasp_nextpnr_ice40-0.9.0.0.post686.dist-info/top_level.txt
yowasp_nextpnr_ice40-0.9.0.0.post686.dist-info/RECORD
